ajsum/__init__.py
ajsum/colorschemes.py
ajsum-0.0.2.dist-info/LICENSE
ajsum-0.0.2.dist-info/METADATA
ajsum-0.0.2.dist-info/WHEEL
ajsum-0.0.2.dist-info/top_level.txt
ajsum-0.0.2.dist-info/RECORD
