Metadata-Version: 2.1
Name: ajsum
Version: 0.0.2
Summary: A small package for convenient functions
Home-page: https://github.com/ajsummers/ajsum
Author: Alex Summers
Author-email: ajsummers7@gmail.com
License: UNKNOWN
Platform: UNKNOWN
Classifier: Programming Language :: Python :: 3
Classifier: License :: OSI Approved :: MIT License
Classifier: Operating System :: OS Independent
Requires-Python: >=3.6
